# 0x02. Python - import & modules  
## Tasks  
- Write a program that imports the function def add(a, b): from the file add_0.py and prints the result of the addition 1 + 2 = 3
```
guillaume@ubuntu:~/0x02$ cat add_0.py
#!/usr/bin/python3
def add(a, b):
    """My addition function

    Args:
        a: first integer
        b: second integer

    Returns:
        The return value. a + b
    """
    return (a + b)

guillaume@ubuntu:~/0x02$ ./0-add.py
1 + 2 = 3
guillaume@ubuntu:~/0x02$ cat 0-import_add.py
__import__("0-add")
guillaume@ubuntu:~/0x02$ python3 0-import_add.py 
guillaume@ubuntu:~/0x02$ 
```
- Write a program that imports functions from the file calculator_1.py, does some Maths, and prints the result.
```
guillaume@ubuntu:~/0x02$ cat calculator_1.py
#!/usr/bin/python3
def add(a, b):
    """My addition function

    Args:
        a: first integer
        b: second integer

    Returns:
        The return value. a + b
    """
    return (a + b)


def sub(a, b):
    """My subtraction function

    Args:
        a: first integer
        b: second integer

    Returns:
        The return value. a - b
    """
    return (a - b)


def mul(a, b):
    """My multiplication function

    Args:
        a: first integer
        b: second integer

    Returns:
        The return value. a * b
    """
    return (a * b)


def div(a, b):
    """My division function

    Args:
        a: first integer
        b: second integer

    Returns:
        The return value. a / b
    """
    return int(a / b)

guillaume@ubuntu:~/0x02$ ./1-calculation.py
10 + 5 = 15
10 - 5 = 5
10 * 5 = 50
10 / 5 = 2
guillaume@ubuntu:~/0x02$
```
- Write a program that prints the number of and the list of its arguments.
```
guillaume@ubuntu:~/0x02$ ./2-args.py 
0 arguments.
guillaume@ubuntu:~/0x02$ ./2-args.py Hello
1 argument:
1: Hello
guillaume@ubuntu:~/0x02$ ./2-args.py Hello Welcome To The Best School
6 arguments:
1: Hello
2: Welcome
3: To
4: The
5: Best
6: School
guillaume@ubuntu:~/0x02$ 
```
- Write a program that prints the result of the addition of all arguments 
```
guillaume@ubuntu:~/0x02$ ./3-infinite_add.py 1111111111111111111111111111111111111111111111111111111111112222222222222222222222222222222222223435467866765443534434222222254444444444444444444444444444444444444444444444444444444444444444444444444444444444444444444444444444555555555555555555555555555555555555555555555555555555555555555555555555555555555555555555555555555555555555555555555555555555555555555555555555555555666666666666666666666666666666777777777777777777777777777777888888888888888888888888888888899999999999999999999999990000000000000000000 11111111111111111111111111111111111111111111111111222222222222222222222222222333333333333333333334567788888899999999999999999999999999999999999999999999999999999999999999999999999999999999999999999999999999999999999999999999999999999999999999999999999999999999999999999999999999999999999999999999999999999999999999999999999999999999999999999999999999999999999999999999999999999999999999999999999999999999999999999999999999999999999999999999999999999999999999999999999999999999999999999999999999999999999999999999999999999999999999999999999999999999999999999999999999999999999999999999999999999999999999999999999
11111111111111111111111111111111111111111111111111222222222222222222222222222333333333333333333334568900000011111111111111111111111111111111111111111111111111112222222222222222222222222222222222223435467866765443534434222222254444444444444444444444444444444444444444444444444444444444444444444444444444444444444444444444444444555555555555555555555555555555555555555555555555555555555555555555555555555555555555555555555555555555555555555555555555555555555555555555555555555555666666666666666666666666666666777777777777777777777777777777888888888888888888888888888888899999999999999999999999989999999999999999999
guillaume@ubuntu:~/0x02$
```
- Write a program that prints all the names defined by the compiled module hidden_4.pyc (please download it locally).
```
guillaume@ubuntu:~/0x02$ curl -Lso "hidden_4.pyc" "https://github.com/holbertonschool/0x02.py/raw/master/hidden_4.pyc"
guillaume@ubuntu:~/0x02$ ./4-hidden_discovery.py | sort
my_secret_santa
print_hidden
print_school
guillaume@ubuntu:~/0x02$ 
```
- Write a program that imports the variable a from the file variable_load_5.py and prints its value.
```
guillaume@ubuntu:~/0x02$ cat variable_load_5.py
#!/usr/bin/python3
a = 98
"""Simple variable
"""

guillaume@ubuntu:~/0x02$ ./5-variable_load.py
98
guillaume@ubuntu:~/0x02$
```
- a program that imports all functions from the file calculator_1.py and handles basic operations.
```
guillaume@ubuntu:~/0x02$ cat calculator_1.py
#!/usr/bin/python3
def add(a, b):
    """My addition function

    Args:
        a: first integer
        b: second integer

    Returns:
        The return value. a + b
    """
    return (a + b)


def sub(a, b):
    """My subtraction function

    Args:
        a: first integer
        b: second integer

    Returns:
        The return value. a - b
    """
    return (a - b)


def mul(a, b):
    """My multiplication function

    Args:
        a: first integer
        b: second integer

    Returns:
        The return value. a * b
    """
    return (a * b)


def div(a, b):
    """My division function

    Args:
        a: first integer
        b: second integer

    Returns:
        The return value. a / b
    """
    return int(a / b)

guillaume@ubuntu:~/0x02$ ./100-my_calculator.py ; echo $?
Usage: ./100-my_calculator.py <a> <operator> <b>
1
guillaume@ubuntu:~/0x02$ ./100-my_calculator.py 3 + 5 ; echo $?
3 + 5 = 8
0
guillaume@ubuntu:~/0x02$ ./100-my_calculator.py 3 H 5 ; echo $?
Unknown operator. Available operators: +, -, * and /
1
guillaume@ubuntu:~/0x02$
```
- a program that prints #pythoniscool, followed by a new line, in the standard output.
```
guillaume@ubuntu:~/0x02$ ./101-easy_print.py
#pythoniscool
guillaume@ubuntu:~/0x02$ 
```
- Write the Python function def magic_calculation(a, b): that does exactly the same as the following Python bytecode:
```
 3           0 LOAD_CONST               1 (0)
              3 LOAD_CONST               2 (('add', 'sub'))
              6 IMPORT_NAME              0 (magic_calculation_102)
              9 IMPORT_FROM              1 (add)
             12 STORE_FAST               2 (add)
             15 IMPORT_FROM              2 (sub)
             18 STORE_FAST               3 (sub)
             21 POP_TOP

  4          22 LOAD_FAST                0 (a)
             25 LOAD_FAST                1 (b)
             28 COMPARE_OP               0 (<)
             31 POP_JUMP_IF_FALSE       94

  5          34 LOAD_FAST                2 (add)
             37 LOAD_F                1 (b)
             43 CALL_FUNCTIOAST                0 (a)
             40 LOAD_FASTN            2 (2 positional, 0 keyword pair)
             46 STORE_FAST               4 (c)

  6          49 SETUP_LOOP              38 (to 90)
             52 LOAD_GLOBAL              3 (range)
             55 LOAD_CONST               3 (4)
             58 LOAD_CONST               4 (6)
             61 CALL_FUNCTION            2 (2 positional, 0 keyword pair)
             64 GET_ITER
        >>   65 FOR_ITER                21 (to 89)
             68 STORE_FAST               5 (i)

  7          71 LOAD_FAST                2 (add)
             74 LOAD_FAST                4 (c)
             77 LOAD_FAST                5 (i)
             80 CALL_FUNCTION            2 (2 positional, 0 keyword pair)
             83 STORE_FAST               4 (c)
             86 JUMP_ABSOLUTE           65
        >>   89 POP_BLOCK

  8     >>   90 LOAD_FAST                4 (c)
             93 RETURN_VALUE

 10     >>   94 LOAD_FAST                3 (sub)
             97 LOAD_FAST                0 (a)
            100 LOAD_FAST                1 (b)
            103 CALL_FUNCTION            2 (2 positional, 0 keyword pair)
            106 RETURN_VALUE
            107 LOAD_CONST               0 (None)
            110 RETURN_VALUE
```
- a program that prints the alphabet in uppercase, followed by a new line.
```
guillaume@ubuntu:~/0x02$ ./103-fast_alphabet.py
ABCDEFGHIJKLMNOPQRSTUVWXYZ
guillaume@ubuntu:~/0x02$ wc -l 103-fast_alphabet.py
3 103-fast_alphabet.py
guillaume@ubuntu:~/0x02$
```
